{
    "id": "854",
    "name": "Aqua Slash Tazer",
    "link": "https://bravefrontierglobal.fandom.com/wiki/Aqua_Slash_Tazer",
    "thumbnail": "https://vignette.wikia.nocookie.net/bravefrontierglobal/images/4/43/Unit_ills_thum_20565.png/revision/latest/scale-to-width-down/42?cb=20150122173548",
    "element": "Category:Water",
    "rarity": "Category:6★ Rarity (Unit)",
    "cost": "Category:Cost 29",
    "dataID": "20565",
    "gender": "Category:Male Unit",
    "maxLevel": "100",
    "arenaType": "2",
    "colosseumLegality": [
        "Category:Warrior Class",
        "Category:Gladiator Class",
        "Category:Conqueror Class",
        "Category:Hero Class"
    ]
}