{
    "id": "1656",
    "name": "Batman",
    "link": "https://bravefrontierglobal.fandom.com/wiki/Batman",
    "thumbnail": "https://vignette.wikia.nocookie.net/bravefrontierglobal/images/c/c9/Unit_ills_thum_61175.png/revision/latest/scale-to-width-down/42?cb=20190401181014",
    "element": "Category:Dark",
    "rarity": "Category:6★ Rarity (Unit)",
    "cost": "Category:Cost 28",
    "dataID": "61175",
    "gender": "Category:Male Unit",
    "maxLevel": "100",
    "arenaType": "13",
    "colosseumLegality": [
        "Category:Warrior Class",
        "Category:Gladiator Class",
        "Category:Conqueror Class",
        "Category:Hero Class"
    ]
}