{
    "id": "8152",
    "name": "Berserker Korzan",
    "link": "https://bravefrontierglobal.fandom.com/wiki/Berserker_Korzan",
    "thumbnail": "https://vignette.wikia.nocookie.net/bravefrontierglobal/images/c/c7/Unit_ills_thum_810315.png/revision/latest/scale-to-width-down/42?cb=20151125140644",
    "element": "Category:Fire",
    "rarity": "Category:5★ Rarity (Unit)",
    "cost": "Category:Cost 20",
    "dataID": "810315",
    "gender": "Category:Male Unit",
    "maxLevel": "80",
    "arenaType": "3",
    "colosseumLegality": [
        "Category:Warrior Class",
        "Category:Gladiator Class",
        "Category:Conqueror Class",
        "Category:Hero Class"
    ]
}