{
    "id": "813",
    "name": "Burst Emperor",
    "link": "https://bravefrontierglobal.fandom.com/wiki/Burst_Emperor",
    "thumbnail": "https://vignette.wikia.nocookie.net/bravefrontierglobal/images/6/63/Unit_ills_thum_10313.png/revision/latest/scale-to-width-down/42?cb=20141218193553",
    "element": "Category:Fire",
    "rarity": "Category:4★ Rarity (Unit)",
    "cost": "Category:Cost 5",
    "dataID": "10313",
    "gender": "Category:Genderless Unit",
    "maxLevel": null,
    "arenaType": "3",
    "colosseumLegality": [
        "Category:Warrior Class",
        "Category:Gladiator Class",
        "Category:Conqueror Class",
        "Category:Hero Class"
    ]
}