{
    "id": "8109",
    "name": "Dark Tone",
    "link": "https://bravefrontierglobal.fandom.com/wiki/Dark_Tone",
    "thumbnail": "https://vignette.wikia.nocookie.net/bravefrontierglobal/images/4/46/Unit_ills_thum_860035.png/revision/latest/scale-to-width-down/42?cb=20150130084616",
    "element": "Category:Dark",
    "rarity": "Category:3★ Rarity (Unit)",
    "cost": "Category:Cost 1",
    "dataID": "860035",
    "gender": "Category:Genderless Unit",
    "maxLevel": "1",
    "arenaType": "3",
    "colosseumLegality": [
        "Category:Warrior Class",
        "Category:Gladiator Class",
        "Category:Conqueror Class",
        "Category:Hero Class"
    ]
}