{
    "id": "8265",
    "name": "Heroes Fei and Fang",
    "link": "https://bravefrontierglobal.fandom.com/wiki/Heroes_Fei_and_Fang",
    "thumbnail": "https://vignette.wikia.nocookie.net/bravefrontierglobal/images/7/70/Unit_ills_thum_830518.png/revision/latest/scale-to-width-down/42?cb=20170209072605",
    "element": "Category:Earth",
    "rarity": "Category:Omni Evolution Rarity",
    "cost": "Category:Cost 47",
    "dataID": "830518",
    "gender": "Category:Genderless Unit",
    "maxLevel": "150",
    "arenaType": "2",
    "colosseumLegality": [
        "Category:Gladiator Class",
        "Category:Conqueror Class",
        "Category:Hero Class"
    ]
}