{
    "id": "18",
    "name": "Knight Atro",
    "link": "https://bravefrontierglobal.fandom.com/wiki/Knight_Atro",
    "thumbnail": "https://vignette.wikia.nocookie.net/bravefrontierglobal/images/a/a3/Unit_ills_thum_50012.png/revision/latest/scale-to-width-down/42?cb=20131029090939",
    "element": "Category:Light",
    "rarity": "Category:3★ Rarity (Unit)",
    "cost": "Category:Cost 4",
    "dataID": "50012",
    "gender": "Category:Male Unit",
    "maxLevel": "40",
    "arenaType": "2",
    "colosseumLegality": [
        "Category:Warrior Class",
        "Category:Gladiator Class",
        "Category:Conqueror Class",
        "Category:Hero Class"
    ]
}