{
    "id": "895",
    "name": "Noble Sage Fadahl",
    "link": "https://bravefrontierglobal.fandom.com/wiki/Noble_Sage_Fadahl",
    "thumbnail": "https://vignette.wikia.nocookie.net/bravefrontierglobal/images/c/ce/Unit_ills_thum_50664.png/revision/latest/scale-to-width-down/42?cb=20150222163911",
    "element": "Category:Light",
    "rarity": "Category:5★ Rarity (Unit)",
    "cost": "Category:Cost 19",
    "dataID": "50664",
    "gender": "Category:Male Unit",
    "maxLevel": "80",
    "arenaType": "3",
    "colosseumLegality": [
        "Category:Warrior Class",
        "Category:Gladiator Class",
        "Category:Conqueror Class",
        "Category:Hero Class"
    ]
}