{
    "id": "844",
    "name": "Shadow Chakra Oboro",
    "link": "https://bravefrontierglobal.fandom.com/wiki/Shadow_Chakra_Oboro",
    "thumbnail": "https://vignette.wikia.nocookie.net/bravefrontierglobal/images/d/dd/Unit_ills_thum_60155.png/revision/latest/scale-to-width-down/42?cb=20150114171743",
    "element": "Category:Dark",
    "rarity": "Category:6★ Rarity (Unit)",
    "cost": "Category:Cost 26",
    "dataID": "60155",
    "gender": "Category:Male Unit",
    "maxLevel": "100",
    "arenaType": "3",
    "colosseumLegality": [
        "Category:Warrior Class",
        "Category:Gladiator Class",
        "Category:Conqueror Class",
        "Category:Hero Class"
    ]
}