{
    "id": "8502",
    "name": "Zodiacal Apex Ophiuchus",
    "link": "https://bravefrontierglobal.fandom.com/wiki/Zodiacal_Apex_Ophiuchus",
    "thumbnail": "https://vignette.wikia.nocookie.net/bravefrontierglobal/images/d/d5/Unit_ills_thum_730257.png/revision/latest/scale-to-width-down/42?cb=20190227072444",
    "element": "Category:Earth",
    "rarity": "Category:Omni Evolution Rarity",
    "cost": "Category:Cost 60",
    "dataID": "730257",
    "gender": "Category:Female Unit",
    "maxLevel": "150",
    "arenaType": "3",
    "colosseumLegality": [
        "Category:Hero Class"
    ]
}