{
    "id": "1195",
    "name": "聖輝の蒼勇神ハルト",
    "link": "https://bravefrontierglobal.fandom.com/wiki/%E8%81%96%E8%BC%9D%E3%81%AE%E8%92%BC%E5%8B%87%E7%A5%9E%E3%83%8F%E3%83%AB%E3%83%88",
    "thumbnail": "https://vignette.wikia.nocookie.net/bravefrontierglobal/images/9/95/Unit_ills_thum_50876.png/revision/latest/scale-to-width-down/42?cb=20151113012410",
    "element": "Category:Light",
    "rarity": "Category:7★ Rarity (Unit)",
    "cost": "Category:Cost 38",
    "dataID": "50876",
    "gender": "Category:Male Unit",
    "maxLevel": "120",
    "arenaType": "4",
    "colosseumLegality": [
        "Category:Warrior Class",
        "Category:Gladiator Class",
        "Category:Conqueror Class",
        "Category:Hero Class"
    ]
}